RS13036UNO/__init__.py
RS13036UNO/biseccion.py
RS13036UNO/crammer.py
RS13036UNO/gauss.py
RS13036UNO/gauss_jordan.py
RS13036UNO/gauss_seidel.py
RS13036UNO/jacobi.py
RS13036UNO/lu.py
RS13036UNO-0.1.0.dist-info/LICENSE
RS13036UNO-0.1.0.dist-info/METADATA
RS13036UNO-0.1.0.dist-info/WHEEL
RS13036UNO-0.1.0.dist-info/top_level.txt
RS13036UNO-0.1.0.dist-info/RECORD
