Metadata-Version: 2.1
Name: RS13036UNO
Version: 0.1.0
Summary: Librería para resolver sistemas de ecuaciones lineales y no lineales.
Author: Brayan Fernando Ramírez Salinas
Author-email: rs13036@ues.edu.sv
Classifier: Programming Language :: Python :: 3
Classifier: Operating System :: OS Independent
Requires-Python: >=3.6
License-File: LICENSE
Requires-Dist: numpy
